oarepo_loose_validation_builder/builtin_models/__init__.py
oarepo_loose_validation_builder/builtin_models/validity.json
oarepo_loose_validation_builder/errors.json5
oarepo_loose_validation_builder/invenio/__init__.py
oarepo_loose_validation_builder/invenio/invenio_validation_marshmallow_imports.py
oarepo_loose_validation_builder/invenio/invenio_validation_poetry.py
oarepo_loose_validation_builder/invenio/invenio_validity_component.py
oarepo_loose_validation_builder/invenio/templates/invenio_validation_component.py.jinja2
oarepo_loose_validation_builder/invenio/templates/invenio_validation_marshmallow_imports.py.jinja2
oarepo_loose_validation_builder/model_preprocessors/__init__.py
oarepo_loose_validation_builder/model_preprocessors/validation_model.py
oarepo_loose_validation_builder/property_preprocessors/validity.py
oarepo_loose_validation_builder-0.0.2.dist-info/entry_points.txt
oarepo_loose_validation_builder-0.0.2.dist-info/LICENSE
oarepo_loose_validation_builder-0.0.2.dist-info/WHEEL
oarepo_loose_validation_builder-0.0.2.dist-info/METADATA
oarepo_loose_validation_builder-0.0.2.dist-info/RECORD
