Metadata-Version: 2.1
Name: oarepo-loose-validation-builder
Version: 0.0.2
Summary: 
Author: Alzbeta Pokorna
Author-email: alzbeta.pokorna@cesnet.cz
Requires-Python: >=3.10,<4.0
Classifier: Programming Language :: Python :: 3
Classifier: Programming Language :: Python :: 3.10
Provides-Extra: json5
Provides-Extra: pyyaml
Requires-Dist: Jinja2 (>=3.0.3,<4.0.0)
Requires-Dist: PyYAML (>=6.0,<7.0); extra == "pyyaml"
Requires-Dist: click (>=7.1)
Requires-Dist: isort (>=5.10.1,<6.0.0)
Requires-Dist: json5 (>=0.9.6,<0.10.0); extra == "json5"
Requires-Dist: jsonpointer (>=2.2,<3.0)
Requires-Dist: langcodes (>=3.3.0)
Requires-Dist: libcst (>=0.4.1,<0.5.0)
Requires-Dist: marshmallow (>=3.14.1,<4.0.0)
Requires-Dist: oarepo-model-builder (>=0.9.17)
Requires-Dist: tomlkit (>=0.9.0,<0.10.0)
